unischeduler/__init__.py
unischeduler/models.py
unischeduler/scheduler.py
unischeduler/scrapper.py
unischeduler/text_parser.py
unischeduler/util.py
unischeduler-0.1.2.dist-info/LICENSE
unischeduler-0.1.2.dist-info/METADATA
unischeduler-0.1.2.dist-info/WHEEL
unischeduler-0.1.2.dist-info/top_level.txt
unischeduler-0.1.2.dist-info/RECORD
