Metadata-Version: 2.1
Name: unischeduler
Version: 0.1.2
Summary: Converts class schedule from text to an icalendar format to export into any known calendar service (google calendar, apple calendar, outlook calendar, etc)
Home-page: UNKNOWN
Author: Stanislav Zmiev
Author-email: szmiev2000@gmail.com
License: MIT
Project-URL: Source Code, https://github.com/Varabe/unischeduler
Platform: UNKNOWN
Classifier: Development Status :: 5 - Production/Stable
Classifier: Environment :: Console
Classifier: Intended Audience :: Developers
Classifier: License :: OSI Approved :: MIT License
Classifier: Natural Language :: English
Classifier: Operating System :: OS Independent
Classifier: Programming Language :: Python :: 3
Classifier: Programming Language :: Python :: 3.6
Classifier: Programming Language :: Python :: 3.7
Requires-Dist: icalendar
Requires-Dist: bs4
Requires-Dist: requests
